{
  "products": [
    {
      "id": 1,
      "productName": "Cosmic Byte H11 Gaming Wired Gaming Overhead-Headset ",
      "categoryId": 1,
      "description": "Over-The-Ear Headphone ",
      "price": "₹899",
      "is_available": false,
      "productImg": "https://i.postimg.cc/bNrjxYHs/h11-gaming-cosmic-byte-original-imafvw6hxgf7tchg.webp",
      "rating": "4.7",
      "review": "47,000",
      "warranty": 2
    },
    {
      "id": 2,
      "productName": "Wings Phantom Gaming TWS Airpods",
      "categoryId": 2,
      "description": "Airpods",
      "price": "₹850",
      "is_available": true,
      "productImg": "https://i.postimg.cc/DZGRjmpc/original-imagf362ucca9yrz.webp",
      "rating": "4.3",
      "review": "4300",
      "warranty": 2
    },
    {
      "id": 3,
      "productName": "Redgear Cloak Wired Gaming Over-Headset ",
      "categoryId": 1,
      "description": "Over-The-Ear Headphone ",
      "price": "₹499",
      "is_available": true,
      "productImg": "https://i.postimg.cc/JzRzCCb8/original-image8f8twewzdzb.webp",
      "rating": "4.1",
      "review": "4155",
      "warranty": 1
    },
    {
      "id": 4,
      "productName": "LaptopAroma NB119 Titanium Bluetooth Headset",
      "categoryId": 3,
      "description": "Bluetooth Headsets",
      "price": "₹499",
      "is_available": true,
      "productImg": "https://i.postimg.cc/50LgZrch/nb119-titanium-48-hours-bluetooth-neckband-aroma-original-imag7qvc7tw4yfwe.webp",
      "rating": "4.8",
      "review": "4855",
      "warranty": 0
    },
    {
      "id": 5,
      "productName": "boAt Airdopes 161 with ASAP Charge, 10mm Drivers",
      "categoryId": 2,
      "description": "Airpods",
      "price": "₹1,199",
      "is_available": true,
      "productImg": "https://i.postimg.cc/MTRk9xWV/original-imagg8mrnmbvphd9.webp",
      "rating": "4.6",
      "review": "40,000",
      "warranty": 1
    },
    {
      "id": 6,
      "productName": "boAt Rockerz 235 Pro ASAP Charge Bluetooth Headsets",
      "categoryId": 3,
      "description": "Bluetooth Headsets",
      "price": "₹999",
      "is_available": true,
      "productImg": "https://i.postimg.cc/3rV9F6NC/original-imagduskzq2my6td.webp",
      "rating": "4.1",
      "review": "4500",
      "warranty": 1
    },
    {
      "id": 7,
      "productName": "Urbanista MIAMI Bluetooth Headset",
      "categoryId": "1",
      "description": "Over-The-Ear Headphones",
      "price": "₹14,399",
      "is_available": "true",
      "productImg": "https://i.postimg.cc/cJQ0L7q8/miami-urbanista-original-imagapntk8yw4mna.webp",
      "rating": "4.5",
      "review": "1000",
      "warranty": "2"
    },
    {
      "id": 8,
      "productName": "Airdopes 161 with ASAP Charge, 10mm Drivers",
      "categoryId": 2,
      "description": "Airpods",
      "price": "₹599",
      "isAvailable": "true",
      "productImg": "https://i.postimg.cc/DwVcmB0R/original-imaghhtnu8zm6yaf.webp",
      "rating": "4",
      "review": "45,999",
      "warrenty": "1",
      "is_available": "true",
      "warranty": "2"
    },
    {
      "id": "9",
      "productName": "pinaaki HIGH BASS Premium Quality Extra Bass Headphone WITH MIC Bluetooth Overhead-Headset ",
      "categoryId": 1,
      "description": "Over-The-Ear Headphones",
      "price": "₹521",
      "isAvailable": "true",
      "productImg": "https://i.postimg.cc/Dz7KymKZ/pinaaki-high-bass-premium-quality-extra-bass-headphone-with-mic-original-imafhzkza9jhnbcq.webp",
      "rating": "4.5",
      "review": "4521",
      "warrenty": "1"
    },
    {
      "id": "10",
      "productName": "Boult Audio ProBass Fcharge with 40 hrs Playtime, ENC, Fast Charging, Fast Pairing Bluetooth Headset ",
      "categoryId": 3,
      "description": "Bluetooth Headphone ",
      "price": "₹998",
      "isAvailable": "false",
      "productImg": "https://i.postimg.cc/ZRGWQ61n/original-imagg33vgs8zzr3j.webp",
      "rating": "4.7",
      "review": "47,000",
      "warrenty": "2"
    },
    {
      "id": "11",
      "productName": "UMORK Earbuds TWS 0.2 Black Airdopes",
      "categoryId": 2,
      "description": "Airpods",
      "price": "₹499",
      "isAvailable": "true",
      "productImg": "https://i.postimg.cc/76xs2TBC/i12-black-headphone-crezor-original-imagdtsgvaz9kdcc.webp",
      "rating": "4.5",
      "review": "45,135",
      "warrenty": "1"
    },
    {
      "id": "12",
      "productName": "Ubon Wireless Headphone with Up to 8Hrs Playtime, Support TF Card, AUX & FM, BT-5750 Bluetooth Overhead-Headset ",
      "categoryId": 1,
      "description": "Over-The-Ear Headphones",
      "price": "₹899",
      "isAvailable": "true",
      "productImg": "https://i.postimg.cc/MHfyM68M/wireless-headphone-with-up-to-8hrs-playtime-support-tf-card-aux-original-imagjpw4vr6zkqyu.webp",
      "rating": "4.1",
      "review": "45,135",
      "warrenty": "2"
    },
    {
      "id": "13",
      "productName": "OPPO Enco M32 Bluetooth Headset  ",
      "categoryId": 3,
      "description": "Bluetooth Headset",
      "price": "₹1,499",
      "isAvailable": "true",
      "productImg": "https://i.postimg.cc/9fGXfsSm/original-imagddshbh6jhbnt.webp",
      "rating": "4",
      "review": "48,999",
      "warrenty": "2"
    },
    {
      "id": "14",
      "productName": "ZEBRONICS Zeb Duke 1 Wireless Headphone with Mic Bluetooth Headset ",
      "categoryId": "1",
      "description": "Over-The-Ear Headphones",
      "price": "₹899",
      "isAvailable": "true",
      "productImg": "https://i.postimg.cc/d19fDZZt/original-imaga2fqu7gdf3aq.webp",
      "rating": "4.1",
      "review": "73",
      "warrenty": "1"
    },
    {
      "id": "15",
      "productName": "DigiClues Gaming Pro Series M5 Earbuds, Headphones Bluetooth Headset ",
      "categoryId": "2",
      "description": "BlutoothAirpod",
      "price": "₹999",
      "isAvailable": "true",
      "productImg": "https://i.postimg.cc/j5wV54Y6/gaming-pro-series-m5-earbuds-tws-buds-5-1-earbuds-with-280h-original-imaghx42j9agxy7e.webp",
      "rating": "3.8",
      "review": "150",
      "warrenty": "NA"
    },
    {
      "id": "21",
      "productName": "UMORK Earbuds TWS 0.2 Black Bluetooth Headset",
      "categoryId": "3",
      "description": "Bluetooth Headset",
      "price": "₹999",
      "isAvailable": "true",
      "productImg": "https://i.postimg.cc/Wz26V3fx/bullets-wireless-z2-oneplus-original-imagfaww7ga6nshz.webp",
      "rating": "4.1",
      "review": "4345",
      "warrenty": "NA"
    }
  ]
}